LICENSE
MANIFEST.in
README.rst
buildout.cfg
develop.cfg
requirements.txt
setup.py
version.txt
bob/__init__.py
bob.ip.optflow.liu.egg-info/PKG-INFO
bob.ip.optflow.liu.egg-info/SOURCES.txt
bob.ip.optflow.liu.egg-info/dependency_links.txt
bob.ip.optflow.liu.egg-info/entry_points.txt
bob.ip.optflow.liu.egg-info/not-zip-safe
bob.ip.optflow.liu.egg-info/requires.txt
bob.ip.optflow.liu.egg-info/top_level.txt
bob/ip/__init__.py
bob/ip/optflow/__init__.py
bob/ip/optflow/liu/__init__.py
bob/ip/optflow/liu/test.py
bob/ip/optflow/liu/version.cpp
bob/ip/optflow/liu/cg_based/GaussianPyramid.cpp
bob/ip/optflow/liu/cg_based/GaussianPyramid.h
bob/ip/optflow/liu/cg_based/Image.h
bob/ip/optflow/liu/cg_based/ImageProcessing.h
bob/ip/optflow/liu/cg_based/OpticalFlow.cpp
bob/ip/optflow/liu/cg_based/OpticalFlow.h
bob/ip/optflow/liu/cg_based/main.cpp
bob/ip/optflow/liu/cg_based/project.h
bob/ip/optflow/liu/data/color/car1.png
bob/ip/optflow/liu/data/color/car2.png
bob/ip/optflow/liu/data/color/rubberwhale1.png
bob/ip/optflow/liu/data/color/rubberwhale2.png
bob/ip/optflow/liu/data/color/table1.png
bob/ip/optflow/liu/data/color/table2.png
bob/ip/optflow/liu/data/color/cg/car.hdf5
bob/ip/optflow/liu/data/gray/car1.png
bob/ip/optflow/liu/data/gray/car2.png
bob/ip/optflow/liu/data/gray/complex1.png
bob/ip/optflow/liu/data/gray/complex2.png
bob/ip/optflow/liu/data/gray/simple1.png
bob/ip/optflow/liu/data/gray/simple2.png
bob/ip/optflow/liu/data/gray/table1.png
bob/ip/optflow/liu/data/gray/table2.png
bob/ip/optflow/liu/data/gray/cg/table.hdf5
bob/ip/optflow/liu/data/gray/sor/table.hdf5
bob/ip/optflow/liu/script/__init__.py
bob/ip/optflow/liu/script/flow.py
bob/ip/optflow/liu/sor_based/GaussianPyramid.cpp
bob/ip/optflow/liu/sor_based/GaussianPyramid.h
bob/ip/optflow/liu/sor_based/Image.h
bob/ip/optflow/liu/sor_based/ImageProcessing.h
bob/ip/optflow/liu/sor_based/NoiseModel.h
bob/ip/optflow/liu/sor_based/OpticalFlow.cpp
bob/ip/optflow/liu/sor_based/OpticalFlow.h
bob/ip/optflow/liu/sor_based/Stochastic.cpp
bob/ip/optflow/liu/sor_based/Stochastic.h
bob/ip/optflow/liu/sor_based/Vector.h
bob/ip/optflow/liu/sor_based/main.cpp
bob/ip/optflow/liu/sor_based/project.h
doc/conf.py
doc/guide.rst
doc/index.rst
doc/links.rst
doc/py_api.rst
matlab/cg_based/demoflow.m
matlab/cg_based/flowimage.m
