Metadata-Version: 1.1
Name: bob.ip.optflow.liu
Version: 2.0.13
Summary: Ce Liu's Optical Flow Framework for Bob
Home-page: https://gitlab.idiap.ch/bob/bob.ip.optflow.liu
Author: Andre Anjos
Author-email: andre.anjos@idiap.ch
License: BSD
Platform: UNKNOWN
Classifier: Framework :: Bob
Classifier: Development Status :: 4 - Beta
Classifier: Intended Audience :: Developers
Classifier: License :: OSI Approved :: BSD License
Classifier: Natural Language :: English
Classifier: Programming Language :: Python
Classifier: Programming Language :: Python :: 3
Classifier: Topic :: Scientific/Engineering :: Artificial Intelligence
Classifier: Topic :: Scientific/Engineering :: Image Recognition
